mcp_tools/__init__.py
mcp_tools/albums.py
mcp_tools/artist_tools.py
mcp_tools/playlist_tools.py
mcp_tools/user_tools.py
spotify_mcp_server.py
spotify_mcp_server-0.1.6.dist-info/METADATA
spotify_mcp_server-0.1.6.dist-info/WHEEL
spotify_mcp_server-0.1.6.dist-info/entry_points.txt
spotify_mcp_server-0.1.6.dist-info/licenses/LICENSE
spotify_mcp_server-0.1.6.dist-info/RECORD
