Metadata-Version: 2.4
Name: spotify-mcp-server
Version: 0.1.6
Summary: Model Context Protocol server for Spotify integration
Project-URL: Homepage, https://github.com/nlevy/spotify-mcp-server
Project-URL: Repository, https://github.com/nlevy/spotify-mcp-server
Project-URL: Issues, https://github.com/nlevy/spotify-mcp-server/issues
Author: Nir Levy
License: MIT
License-File: LICENSE
Keywords: ai,assistant,mcp,model-context-protocol,spotify
Classifier: Development Status :: 3 - Alpha
Classifier: Intended Audience :: Developers
Classifier: License :: OSI Approved :: MIT License
Classifier: Programming Language :: Python :: 3
Classifier: Programming Language :: Python :: 3.10
Classifier: Programming Language :: Python :: 3.11
Classifier: Programming Language :: Python :: 3.12
Classifier: Programming Language :: Python :: 3.13
Requires-Python: >=3.10
Requires-Dist: mcp[cli]>=1.10.1
Requires-Dist: python-dotenv>=1.0.0
Requires-Dist: spotipy>=2.25.1
